{
	"format_version": "1.8.0",
	"animations": {
		"idle": {
			"loop": true,
			"animation_length": 2.625,
			"bones": {
				"all": {
					"rotation": {
						"0.0": {
							"vector": [-7.5, 0, 0]
						},
						"1.375": {
							"vector": [5, 0, 0]
						},
						"2.625": {
							"vector": [-7.5, 0, 0]
						}
					},
					"position": {
						"0.0": {
							"vector": [0, -3, 0]
						},
						"1.375": {
							"vector": [0, 3, 0]
						},
						"2.625": {
							"vector": [0, -3, 0]
						}
					}
				},
				"head1": {
					"rotation": {
						"0.0": {
							"vector": [10, 0, 0]
						},
						"1.375": {
							"vector": [-5, 0, 0]
						},
						"2.625": {
							"vector": [10, 0, 0]
						}
					}
				},
				"mustache_r": {
					"rotation": {
						"0.0": {
							"vector": [0, -17.5, 0]
						},
						"1.375": {
							"vector": [0, 17.5, 0]
						},
						"2.625": {
							"vector": [0, -17.5, 0]
						}
					}
				},
				"mustache_l": {
					"rotation": {
						"0.0": {
							"vector": [0, 17.5, 0]
						},
						"1.375": {
							"vector": [0, -17.5, 0]
						},
						"2.625": {
							"vector": [0, 17.5, 0]
						}
					}
				},
				"bone": {
					"rotation": {
						"0.0": {
							"vector": [0, 0, 0]
						},
						"0.7917": {
							"vector": [14.32, 0, 0]
						},
						"1.7917": {
							"vector": [7.5, 0, 0]
						},
						"2.625": {
							"vector": [0, 0, 0]
						}
					}
				},
				"head2": {
					"scale": {
						"vector": [0, 0, 0]
					}
				},
				"head3": {
					"scale": {
						"vector": [0, 0, 0]
					}
				},
				"normal": {
					"rotation": {
						"0.0": {
							"vector": [0, 0, -5]
						},
						"0.375": {
							"vector": [0, 0, 5]
						},
						"1.0": {
							"vector": [0, 0, 0]
						},
						"1.6667": {
							"vector": [0, 0, -5]
						},
						"2.1667": {
							"vector": [0, 0, 0]
						},
						"2.625": {
							"vector": [0, 0, -5]
						}
					}
				},
				"hand": {
					"rotation": {
						"0.0": {
							"vector": [0, 0, -15]
						},
						"1.375": {
							"vector": [0, 0, 15]
						},
						"2.625": {
							"vector": [0, 0, -15]
						}
					}
				},
				"medium": {
					"rotation": {
						"0.0": {
							"vector": [0, 0, -20]
						},
						"1.375": {
							"vector": [0, 0, 20]
						},
						"2.625": {
							"vector": [0, 0, -20]
						}
					}
				},
				"hand2": {
					"rotation": {
						"0.0": {
							"vector": [0, 0, 15]
						},
						"1.375": {
							"vector": [0, 0, -15]
						},
						"2.625": {
							"vector": [0, 0, 15]
						}
					}
				},
				"tail": {
					"rotation": {
						"0.0": {
							"vector": [10, 0, 0]
						},
						"1.375": {
							"vector": [-5, 0, 0]
						},
						"2.625": {
							"vector": [10, 0, 0]
						}
					}
				},
				"tail_leg": {
					"rotation": {
						"0.0": {
							"vector": [0, -35, 0]
						},
						"1.375": {
							"vector": [0, 35, 0]
						},
						"2.625": {
							"vector": [0, -35, 0]
						}
					}
				},
				"allcircle": {
					"scale": {
						"vector": [0, 0, 0]
					}
				}
			}
		},
		"swim": {
			"loop": true,
			"animation_length": 0.875,
			"bones": {
				"all": {
					"rotation": {
						"0.0": {
							"vector": [-5, 0, 0]
						},
						"0.1667": {
							"vector": [13.44, 0, 0]
						},
						"0.4167": {
							"vector": [12.5, 0, 0]
						},
						"0.6667": {
							"vector": [-6.25, 0, 0]
						},
						"0.875": {
							"vector": [-5, 0, 0]
						}
					},
					"position": {
						"0.0": {
							"vector": [0, -7, 0]
						},
						"0.1667": {
							"vector": [0, -8, -4]
						},
						"0.4167": {
							"vector": [0, 1, -3]
						},
						"0.6667": {
							"vector": [0, 3, 3]
						},
						"0.875": {
							"vector": [0, -7, 0]
						}
					}
				},
				"head1": {
					"rotation": {
						"0.0": {
							"vector": [7.5, 0, 0]
						},
						"0.4167": {
							"vector": [-5, 0, 0]
						},
						"0.875": {
							"vector": [7.5, 0, 0]
						}
					}
				},
				"mustache_r": {
					"rotation": {
						"0.0": {
							"vector": [0, -22.5, 0]
						},
						"0.4167": {
							"vector": [0, 0, 0]
						},
						"0.875": {
							"vector": [0, -22.5, 0]
						}
					}
				},
				"mustache_l": {
					"rotation": {
						"0.0": {
							"vector": [0, 22.5, 0]
						},
						"0.4167": {
							"vector": [0, 0, 0]
						},
						"0.875": {
							"vector": [0, 22.5, 0]
						}
					}
				},
				"bone": {
					"rotation": {
						"0.0": {
							"vector": [7.5, 0, 0]
						},
						"0.4167": {
							"vector": [2.5, 0, 0]
						},
						"0.875": {
							"vector": [7.5, 0, 0]
						}
					}
				},
				"head2": {
					"scale": {
						"vector": [0, 0, 0]
					}
				},
				"head3": {
					"scale": {
						"vector": [0, 0, 0]
					}
				},
				"hand": {
					"rotation": {
						"0.0": {
							"vector": [0, 0, -20]
						},
						"0.1667": {
							"vector": [37.5, 0, 2]
						},
						"0.4167": {
							"vector": [0, 0, 25]
						},
						"0.6667": {
							"vector": [-25, 0, -7.72727]
						},
						"0.875": {
							"vector": [0, 0, -20]
						}
					}
				},
				"medium": {
					"rotation": {
						"0.0": {
							"vector": [0, 0, -17.5]
						},
						"0.4167": {
							"vector": [0, 0, 17.5]
						},
						"0.875": {
							"vector": [0, 0, -17.5]
						}
					}
				},
				"hand2": {
					"rotation": {
						"0.0": {
							"vector": [0, 0, 20]
						},
						"0.1667": {
							"vector": [37.5, 0, 2]
						},
						"0.4167": {
							"vector": [0, 0, -25]
						},
						"0.6667": {
							"vector": [-25, 0, -7.72727]
						},
						"0.875": {
							"vector": [0, 0, 20]
						}
					}
				},
				"tail": {
					"rotation": {
						"0.0": {
							"vector": [10, 0, 0]
						},
						"0.4167": {
							"vector": [-10, 0, 0]
						},
						"0.875": {
							"vector": [10, 0, 0]
						}
					}
				},
				"tail_leg": {
					"rotation": {
						"0.0": {
							"vector": [0, 27.5, 0]
						},
						"0.4167": {
							"vector": [0, -27.5, 0]
						},
						"0.875": {
							"vector": [0, 27.5, 0]
						}
					}
				},
				"allcircle": {
					"scale": {
						"vector": [0, 0, 0]
					}
				}
			}
		},
		"swim_slow": {
			"loop": true,
			"animation_length": 2.04167,
			"bones": {
				"all": {
					"rotation": {
						"0.0": {
							"vector": [-5, 0, 0]
						},
						"0.4167": {
							"vector": [13.44, 0, 0]
						},
						"1.0": {
							"vector": [12.5, 0, 0]
						},
						"1.5417": {
							"vector": [-6.25, 0, 0]
						},
						"2.0417": {
							"vector": [-5, 0, 0]
						}
					},
					"position": {
						"0.0": {
							"vector": [0, 1, 0]
						},
						"0.4167": {
							"vector": [0, -3, 0]
						},
						"1.0": {
							"vector": [0, -3, 0]
						},
						"1.5417": {
							"vector": [0, 0, 0]
						},
						"2.0417": {
							"vector": [0, 1, 0]
						}
					}
				},
				"head1": {
					"rotation": {
						"0.0": {
							"vector": [7.5, 0, 0]
						},
						"1.0": {
							"vector": [-5, 0, 0]
						},
						"2.0417": {
							"vector": [7.5, 0, 0]
						}
					}
				},
				"mustache_r": {
					"rotation": {
						"0.0": {
							"vector": [0, -22.5, 0]
						},
						"1.0": {
							"vector": [0, 0, 0]
						},
						"2.0417": {
							"vector": [0, -22.5, 0]
						}
					}
				},
				"mustache_l": {
					"rotation": {
						"0.0": {
							"vector": [0, 22.5, 0]
						},
						"1.0": {
							"vector": [0, 0, 0]
						},
						"2.0417": {
							"vector": [0, 22.5, 0]
						}
					}
				},
				"bone": {
					"rotation": {
						"0.0": {
							"vector": [7.5, 0, 0]
						},
						"1.0": {
							"vector": [2.5, 0, 0]
						},
						"2.0417": {
							"vector": [7.5, 0, 0]
						}
					}
				},
				"head2": {
					"scale": {
						"vector": [0, 0, 0]
					}
				},
				"head3": {
					"scale": {
						"vector": [0, 0, 0]
					}
				},
				"hand": {
					"rotation": {
						"0.0": {
							"vector": [0, 0, -20]
						},
						"1.0": {
							"vector": [0, 0, 25]
						},
						"2.0417": {
							"vector": [0, 0, -20]
						}
					}
				},
				"medium": {
					"rotation": {
						"0.0": {
							"vector": [0, 0, -17.5]
						},
						"1.0": {
							"vector": [0, 0, 17.5]
						},
						"2.0417": {
							"vector": [0, 0, -17.5]
						}
					}
				},
				"hand2": {
					"rotation": {
						"0.0": {
							"vector": [0, 0, 20]
						},
						"1.0": {
							"vector": [0, 0, -25]
						},
						"2.0417": {
							"vector": [0, 0, 20]
						}
					}
				},
				"tail": {
					"rotation": {
						"0.0": {
							"vector": [10, 0, 0]
						},
						"1.0": {
							"vector": [-10, 0, 0]
						},
						"2.0417": {
							"vector": [10, 0, 0]
						}
					}
				},
				"tail_leg": {
					"rotation": {
						"0.0": {
							"vector": [0, 27.5, 0]
						},
						"1.0": {
							"vector": [0, -27.5, 0]
						},
						"2.0417": {
							"vector": [0, 27.5, 0]
						}
					}
				},
				"allcircle": {
					"scale": {
						"vector": [0, 0, 0]
					}
				}
			}
		},
		"whirlwind": {
			"animation_length": 2.08333,
			"bones": {
				"all": {
					"rotation": {
						"0.0": {
							"vector": [-15, 0, 0]
						},
						"0.4583": {
							"vector": [-25, 0, 0]
						},
						"0.7083": {
							"vector": [-15, 0, 0]
						},
						"0.9167": {
							"vector": [-14.13272, -5.07855, -19.37006]
						},
						"1.1667": {
							"vector": [-15, 0, 0]
						},
						"1.4583": {
							"vector": [-14.13272, -5.07855, -19.37006]
						},
						"1.6667": {
							"vector": [-25, 0, 0]
						},
						"2.0417": {
							"vector": [-15, 0, 0]
						}
					},
					"position": {
						"0.0": {
							"vector": [0, 0, 7]
						},
						"0.25": {
							"vector": [0, 0, -2]
						},
						"1.7083": {
							"vector": [0, 0, 20.56]
						},
						"2.0417": {
							"vector": [0, 0, 7]
						}
					}
				},
				"head1": {
					"scale": {
						"vector": [0, 0, 0]
					}
				},
				"bone": {
					"rotation": {
						"vector": [37.5, 0, 0]
					}
				},
				"head2": {
					"scale": {
						"vector": [0, 0, 0]
					}
				},
				"head3": {
					"rotation": {
						"0.0": {
							"vector": [42.5, 0, 0]
						},
						"0.25": {
							"vector": [55, 0, 0]
						},
						"0.5833": {
							"vector": [32.89913, -12.67956, 18.74227]
						},
						"0.7917": {
							"vector": [34.0724, 8.53726, -12.37961]
						},
						"1.0417": {
							"vector": [32.89913, -12.67956, 18.74227]
						},
						"1.25": {
							"vector": [34.0724, 8.53726, -12.37961]
						},
						"1.5417": {
							"vector": [32.89913, -12.67956, 18.74227]
						},
						"1.75": {
							"vector": [34.0724, 8.53726, -12.37961]
						},
						"1.9167": {
							"vector": [32.89913, -12.67956, 18.74227]
						},
						"2.0417": {
							"vector": [34.0724, 8.53726, -12.37961]
						}
					},
					"position": {
						"0.0": {
							"vector": [0, 0, 15]
						},
						"0.6667": {
							"vector": [0, -3, 10]
						}
					},
					"scale": {
						"vector": [1, 1, 1]
					}
				},
				"body": {
					"rotation": {
						"vector": [12.5, 0, 0]
					}
				},
				"hand": {
					"rotation": {
						"0.0": {
							"vector": [0, 0, -17.5]
						},
						"0.75": {
							"vector": [0, 0, 70]
						},
						"1.75": {
							"vector": [0, 0, -17.5]
						}
					}
				},
				"medium": {
					"rotation": {
						"0.0": {
							"vector": [0, 0, 52.5]
						},
						"0.4583": {
							"vector": [0, 0, -52.5]
						},
						"1.0417": {
							"vector": [0, 0, 52.5]
						},
						"1.5": {
							"vector": [0, 0, -52.5]
						},
						"2.0833": {
							"vector": [0, 0, 52.5]
						}
					}
				},
				"hand2": {
					"rotation": {
						"0.0": {
							"vector": [0, 0, 17.5]
						},
						"0.75": {
							"vector": [0, 0, -70]
						},
						"1.75": {
							"vector": [0, 0, 17.5]
						}
					}
				},
				"tail": {
					"rotation": {
						"0.0": {
							"vector": [-45, 0, 0]
						},
						"0.6667": {
							"vector": [32.5, 0, 0]
						},
						"1.4167": {
							"vector": [-17.5, 0, 0]
						},
						"2.0": {
							"vector": [-12.5, 0, 0]
						}
					}
				},
				"tail_leg": {
					"rotation": {
						"0.0": {
							"vector": [0, -20, 0]
						},
						"0.5833": {
							"vector": [0, 20, 0]
						},
						"1.125": {
							"vector": [0, -20, 0]
						},
						"1.5417": {
							"vector": [0, 20, 0]
						},
						"2.0": {
							"vector": [0, -20, 0]
						}
					}
				},
				"bone2": {
					"relative_to": {
						"rotation": "entity"
					},
					"rotation": {
						"0.4583": {
							"vector": [0, 0, 0]
						},
						"1.625": {
							"vector": [0, 0, 360]
						}
					},
					"position": {
						"0.4583": {
							"vector": [0, 0, -76]
						},
						"1.625": {
							"vector": [0, 0, -39]
						}
					},
					"scale": {
						"0.4167": {
							"vector": [0, 0, 0]
						},
						"0.4583": {
							"vector": [20.6, 20.6, 20.6]
						},
						"1.2917": {
							"vector": [9, 9, 9]
						},
						"1.5417": {
							"vector": [0, 0, 0]
						}
					}
				},
				"bone4": {
					"relative_to": {
						"rotation": "entity"
					},
					"rotation": {
						"0.5": {
							"vector": [0, 0, 0]
						},
						"2.0417": {
							"vector": [0, 0, 360]
						}
					},
					"position": {
						"0.5": {
							"vector": [0, 0, -53]
						},
						"2.0417": {
							"vector": [0, 0, -5]
						}
					},
					"scale": {
						"0.4583": {
							"vector": [0, 0, 0]
						},
						"0.5": {
							"vector": [15, 15, 15]
						},
						"0.8333": {
							"vector": [16, 16, 16]
						},
						"1.3333": {
							"vector": [12, 12, 12]
						},
						"1.9583": {
							"vector": [0, 0, 0]
						}
					}
				},
				"bone3": {
					"relative_to": {
						"rotation": "entity"
					},
					"rotation": {
						"0.4583": {
							"vector": [0, 0, 0]
						},
						"1.5833": {
							"vector": [0, 0, 360]
						}
					},
					"position": {
						"0.4583": {
							"vector": [0, 0, -67]
						},
						"1.5833": {
							"vector": [0, 0, -27]
						}
					},
					"scale": {
						"0.4167": {
							"vector": [0, 0, 0]
						},
						"0.4583": {
							"vector": [15, 15, 15]
						},
						"1.125": {
							"vector": [15, 15, 15]
						},
						"1.5": {
							"vector": [0, 0, 0]
						}
					}
				}
			}
		},
		"eat": {
			"animation_length": 0.58333,
			"bones": {
				"all": {
					"rotation": {
						"0.0": {
							"vector": [-10, 0, 0]
						},
						"0.0833": {
							"vector": [-4.92442, -0.86717, -9.96271]
						},
						"0.1667": {
							"vector": [-0.02538, -0.28904, 6.67922]
						},
						"0.5833": {
							"vector": [2.5, 0, 0]
						}
					}
				},
				"head": {
					"rotation": {
						"0.0": {
							"vector": [-10, 0, 0]
						},
						"0.125": {
							"vector": [22.5, 0, 0]
						},
						"0.25": {
							"vector": [-5, 0, 0]
						},
						"0.5833": {
							"vector": [-10, 0, 0]
						}
					},
					"position": {
						"0.0": {
							"vector": [0, 0, 0]
						},
						"0.0833": {
							"vector": [0, 2, 1.5]
						},
						"0.125": {
							"vector": [0, 3, 0]
						},
						"0.1667": {
							"vector": [0, 2, 1.5]
						},
						"0.2083": {
							"vector": [0, 1, 2]
						},
						"0.25": {
							"vector": [0, 0, 0]
						},
						"0.5833": {
							"vector": [0, 0, 0]
						}
					}
				},
				"head1": {
					"rotation": {
						"vector": [5, 0, 0]
					},
					"position": {
						"vector": [0, 0.75, -1.25]
					},
					"scale": {
						"0.0": {
							"vector": [0, 0, 0]
						},
						"0.25": {
							"vector": [0, 0, 0]
						},
						"0.2917": {
							"vector": [1, 1, 1]
						}
					}
				},
				"head2": {
					"rotation": {
						"0.0": {
							"vector": [-7.5, 0, 0]
						},
						"0.1667": {
							"vector": [5, 0, 0]
						}
					},
					"position": {
						"vector": [0, 0, -1]
					},
					"scale": {
						"0.0": {
							"vector": [1, 1, 1]
						},
						"0.2917": {
							"vector": [1, 1, 1]
						},
						"0.3333": {
							"vector": [0, 0, 0]
						}
					}
				},
				"head3": {
					"scale": {
						"vector": [0, 0, 0]
					}
				},
				"body": {
					"rotation": {
						"0.0": {
							"vector": [-10, 0, 0]
						},
						"0.0833": {
							"vector": [5, 0, 0]
						},
						"0.125": {
							"vector": [4.95744, 0.65182, -7.47178]
						},
						"0.1667": {
							"vector": [4.95744, -0.65182, 7.47178]
						},
						"0.5833": {
							"vector": [-10, 0, 0]
						}
					}
				},
				"hand": {
					"rotation": {
						"0.0": {
							"vector": [-31.27913, 7.9332, -6.9035]
						},
						"0.125": {
							"vector": [-18.66225, 26.6906, 33.3562]
						},
						"0.5833": {
							"vector": [-31.27913, 7.9332, -6.9035]
						}
					}
				},
				"hand2": {
					"rotation": {
						"0.0": {
							"vector": [-31.27913, -7.93322, 6.90354]
						},
						"0.125": {
							"vector": [-18.66225, -26.69062, -33.35618]
						},
						"0.5833": {
							"vector": [-31.27913, -7.93322, 6.90354]
						}
					}
				},
				"tail": {
					"rotation": {
						"0.0": {
							"vector": [-17.5, 0, 0]
						},
						"0.125": {
							"vector": [30, 0, 0]
						},
						"0.5833": {
							"vector": [-17.5, 0, 0]
						}
					}
				},
				"mouthgiant": {
					"position": {
						"0.0": {
							"vector": [0, 0.5, 0]
						},
						"0.25": {
							"vector": [0, 1.5, 0]
						}
					},
					"scale": {
						"0.0": {
							"vector": [1, 0.8, 1]
						},
						"0.1667": {
							"vector": [1, 1, 1]
						},
						"0.25": {
							"vector": [1, 0.2, 1]
						}
					}
				},
				"allcircle": {
					"scale": {
						"vector": [0, 0, 0]
					}
				}
			}
		},
		"throwup": {
			"animation_length": 0.75,
			"bones": {
				"all": {
					"rotation": {
						"0.0": {
							"vector": [0, 0, 0]
						},
						"0.1667": {
							"vector": [-20, 0, 0]
						},
						"0.2917": {
							"vector": [-19.5623, -4.2453, -11.76782]
						},
						"0.4167": {
							"vector": [-19.37006, 5.07855, 14.13272]
						},
						"0.5": {
							"vector": [0, 0, 0]
						},
						"0.625": {
							"vector": [0, 0, 0]
						}
					}
				},
				"head1": {
					"rotation": {
						"0.5417": {
							"vector": [-7.5, 0, 0]
						},
						"0.6667": {
							"vector": [5, 0, 0]
						}
					},
					"scale": {
						"0.0": {
							"vector": [0, 0, 0]
						},
						"0.5417": {
							"vector": [0, 0, 0]
						},
						"0.5833": {
							"vector": [1, 1, 1]
						}
					}
				},
				"head2": {
					"rotation": {
						"0.0": {
							"vector": [0, 0, 0]
						},
						"0.0833": {
							"vector": [4.43191, 0.78064, -9.96979]
						},
						"0.1667": {
							"vector": [22.5, 0, 0]
						},
						"0.25": {
							"vector": [21.55613, -6.60796, 16.24074]
						},
						"0.3333": {
							"vector": [-15, 0, 0]
						},
						"0.4583": {
							"vector": [7.5, 0, 0]
						},
						"0.5417": {
							"vector": [-5, 0, 0]
						},
						"0.5833": {
							"vector": [0, 0, 0]
						}
					},
					"position": {
						"0.4167": {
							"vector": [0, -1, -1]
						},
						"0.5417": {
							"vector": [0, 0, 0]
						}
					},
					"scale": {
						"0.5833": {
							"vector": [1, 1, 1]
						},
						"0.625": {
							"vector": [0, 0, 0]
						}
					}
				},
				"mouthgiant": {
					"position": {
						"0.375": {
							"vector": [0, 1, 0]
						},
						"0.5833": {
							"vector": [0, 1, 0]
						}
					},
					"scale": {
						"0.0": {
							"vector": [1, 1, 1]
						},
						"0.0833": {
							"vector": [1, 0.7, 1]
						},
						"0.1667": {
							"vector": [1, 1, 1]
						},
						"0.25": {
							"vector": [0.5, 0.425, 1]
						},
						"0.375": {
							"vector": [0.5, 0.425, 1]
						},
						"0.5833": {
							"vector": [0.5, 0.125, 1]
						},
						"0.625": {
							"vector": [0, 0, 0]
						}
					}
				},
				"head3": {
					"scale": {
						"vector": [0, 0, 0]
					}
				},
				"normal": {
					"rotation": {
						"vector": [-5, 0, 0]
					}
				},
				"hand": {
					"rotation": {
						"0.0": {
							"vector": [0, 0, 0]
						},
						"0.0417": {
							"vector": [0, 0, -25]
						},
						"0.1667": {
							"vector": [0, 0, 27.5]
						},
						"0.25": {
							"vector": [0, 0, -17.5]
						},
						"0.3333": {
							"vector": [0, 0, 27.5]
						},
						"0.4167": {
							"vector": [0, 0, -17.5]
						},
						"0.5": {
							"vector": [0, 0, 27.5]
						},
						"0.6667": {
							"vector": [0, 0, -25]
						},
						"0.75": {
							"vector": [0, 0, 0]
						}
					}
				},
				"hand2": {
					"rotation": {
						"0.0": {
							"vector": [0, 0, 0]
						},
						"0.0417": {
							"vector": [0, 0, -25]
						},
						"0.1667": {
							"vector": [0, 0, 27.5]
						},
						"0.25": {
							"vector": [0, 0, -17.5]
						},
						"0.3333": {
							"vector": [0, 0, 27.5]
						},
						"0.4167": {
							"vector": [0, 0, -17.5]
						},
						"0.5": {
							"vector": [0, 0, 27.5]
						},
						"0.6667": {
							"vector": [0, 0, -25]
						},
						"0.75": {
							"vector": [0, 0, 0]
						}
					}
				},
				"allcircle": {
					"scale": {
						"vector": [0, 0, 0]
					}
				}
			}
		},
		"swim_mouthopen": {
			"loop": true,
			"animation_length": 0.875,
			"bones": {
				"all": {
					"rotation": {
						"0.0": {
							"vector": [-5, 0, 0]
						},
						"0.1667": {
							"vector": [13.44, 0, 0]
						},
						"0.4167": {
							"vector": [12.5, 0, 0]
						},
						"0.6667": {
							"vector": [-6.25, 0, 0]
						},
						"0.875": {
							"vector": [-5, 0, 0]
						}
					},
					"position": {
						"0.0": {
							"vector": [0, -7, 0]
						},
						"0.1667": {
							"vector": [0, -8, -4]
						},
						"0.4167": {
							"vector": [0, 1, -3]
						},
						"0.6667": {
							"vector": [0, 3, 3]
						},
						"0.875": {
							"vector": [0, -7, 0]
						}
					}
				},
				"head1": {
					"scale": {
						"vector": [0, 0, 0]
					}
				},
				"mustache_r": {
					"rotation": {
						"0.0": {
							"vector": [0, -22.5, 0]
						},
						"0.4167": {
							"vector": [0, 0, 0]
						},
						"0.875": {
							"vector": [0, -22.5, 0]
						}
					}
				},
				"mustache_l": {
					"rotation": {
						"0.0": {
							"vector": [0, 22.5, 0]
						},
						"0.4167": {
							"vector": [0, 0, 0]
						},
						"0.875": {
							"vector": [0, 22.5, 0]
						}
					}
				},
				"bone": {
					"rotation": {
						"0.0": {
							"vector": [7.5, 0, 0]
						},
						"0.4167": {
							"vector": [2.5, 0, 0]
						},
						"0.875": {
							"vector": [7.5, 0, 0]
						}
					}
				},
				"head2": {
					"rotation": {
						"0.0": {
							"vector": [5, 0, 0]
						},
						"0.2083": {
							"vector": [-13.75, 0, 0]
						},
						"0.4167": {
							"vector": [-12.5, 0, 0]
						},
						"0.625": {
							"vector": [1.59, 0, 0]
						},
						"0.875": {
							"vector": [7.5, 0, 0]
						}
					},
					"scale": {
						"vector": [1, 1, 1]
					}
				},
				"head3": {
					"scale": {
						"vector": [0, 0, 0]
					}
				},
				"hand": {
					"rotation": {
						"0.0": {
							"vector": [0, 0, -20]
						},
						"0.1667": {
							"vector": [37.5, 0, 2]
						},
						"0.4167": {
							"vector": [0, 0, 25]
						},
						"0.6667": {
							"vector": [-25, 0, -7.72727]
						},
						"0.875": {
							"vector": [0, 0, -20]
						}
					}
				},
				"medium": {
					"rotation": {
						"0.0": {
							"vector": [0, 0, -17.5]
						},
						"0.4167": {
							"vector": [0, 0, 17.5]
						},
						"0.875": {
							"vector": [0, 0, -17.5]
						}
					}
				},
				"hand2": {
					"rotation": {
						"0.0": {
							"vector": [0, 0, 20]
						},
						"0.1667": {
							"vector": [37.5, 0, 2]
						},
						"0.4167": {
							"vector": [0, 0, -25]
						},
						"0.6667": {
							"vector": [-25, 0, -7.72727]
						},
						"0.875": {
							"vector": [0, 0, 20]
						}
					}
				},
				"tail": {
					"rotation": {
						"0.0": {
							"vector": [10, 0, 0]
						},
						"0.4167": {
							"vector": [-10, 0, 0]
						},
						"0.875": {
							"vector": [10, 0, 0]
						}
					}
				},
				"tail_leg": {
					"rotation": {
						"0.0": {
							"vector": [0, 27.5, 0]
						},
						"0.4167": {
							"vector": [0, -27.5, 0]
						},
						"0.875": {
							"vector": [0, 27.5, 0]
						}
					}
				},
				"mouthgiant": {
					"scale": {
						"0.0": {
							"vector": [1, 1, 1]
						},
						"0.2083": {
							"vector": [1, 1.2, 1]
						},
						"0.5417": {
							"vector": [1, 1.4, 1]
						},
						"0.875": {
							"vector": [1, 1, 1]
						}
					}
				},
				"allcircle": {
					"scale": {
						"vector": [0, 0, 0]
					}
				}
			}
		}
	},
	"geckolib_format_version": 2
}